realtimefunc/__init__.py
realtimefunc/realtimefunc.py
realtimefunc-0.1.1.dist-info/LICENSE
realtimefunc-0.1.1.dist-info/METADATA
realtimefunc-0.1.1.dist-info/WHEEL
realtimefunc-0.1.1.dist-info/top_level.txt
realtimefunc-0.1.1.dist-info/RECORD
