Metadata-Version: 2.1
Name: realtimefunc
Version: 0.1.1
Summary: A decorator is used to update a function at runtime.
Home-page: https://github.com/Graywd/realtimefunc
Author: Graywd
Author-email: nowreturnlong@gmail.com
License: UNKNOWN
Platform: UNKNOWN
Classifier: Programming Language :: Python :: 2.7
Classifier: Programming Language :: Python :: 3.6
Classifier: Programming Language :: Python :: 3.7
Classifier: License :: OSI Approved :: MIT License
Classifier: Operating System :: OS Independent
